{
  "url": "https://immi.homeaffairs.gov.au/visas/getting-a-visa/visa-listing/business-innovation-and-investment-888/",
  "title": "Business Innovation and Investment (Permanent) visa",
  "raw_text": "===== main placeholder ========================================== Subclass 888 Business Innovation and Investment (Permanent) visa For entrepreneurs, investors and business owners to continue their activity in Australia. Basic Eligibility hold a relevant stream of the subclass 188 visa or in relation to applications for a subclass 888 visa in the Business Innovation stream, hold a relevant stream of the subclass 188 visa, or a subclass 444 (Special Category) visa, or a subclass 457 (Business (Long Stay)) visa granted in certain circumstances.",
  "main_content": "===== main placeholder ==========================================\n\nSubclass 888\n\nSubclass 888\n\n# Business Innovation and Investment (Permanent) visa\n\nBusiness Innovation and Investment (Permanent) visa\n\nFor entrepreneurs, investors and business owners to continue their activity in Australia.\n\nFor entrepreneurs, investors and business owners to continue their activity in Australia.\n\n### Basic Eligibility\n\nBasic Eligibility\n- hold a relevant stream of the subclass 188 visa or in relation to applications for a subclass 888 visa in the Business Innovation stream, hold a relevant stream of the subclass 188 visa, or a subclass 444 (Special Category) visa, or a subclass 457 (Business (Long Stay)) visa granted in certain circumstances.\nhold a relevant stream of the subclass 188 visa or in relation to applications for a subclass 888 visa in the Business Innovation stream, hold a relevant stream of the subclass 188 visa, or a subclass 444 (Special Category) visa, or a subclass 457 (Business (Long Stay)) visa granted in certain circumstances.",
  "interactive_sections": [],
  "referenced_links": [],
  "discovered_links": [
    "https://immi.homeaffairs.gov.au/visas/getting-a-visa/visa-listing/business-innovation-and-investment-888/#contentBox",
    "https://immi.homeaffairs.gov.au/visas/getting-a-visa/visa-listing/business-innovation-and-investment-888/#top"
  ],
  "parent_url": "https://immi.homeaffairs.gov.au/visas/getting-a-visa/visa-listing",
  "depth": 1,
  "scraped_at": "2026-01-05T15:11:33.889704",
  "metadata": {}
}