{
  "url": "https://immi.homeaffairs.gov.au/visas/getting-a-visa/visa-listing/skills-in-demand-visa-subclass-482",
  "title": "Skills in Demand",
  "content_type": "visa_information",
  "summary": "This page provides information about the Subclass 482 Skills in Demand visa. It outlines that the visa allows employers to sponsor skilled overseas workers when suitably skilled Australians are not available. The content includes a brief description and the basic eligibility criteria applicants must meet.",
  "structured_data": {
    "visa_name": "Skills in Demand",
    "visa_subclass": "482",
    "visa_type": "temporary",
    "description": "This temporary visa lets an employer sponsor a suitably skilled worker to fill a position they can’t find a suitably skilled Australian to fill.",
    "eligibility": {
      "basic_eligibility_requirements": [
        "Be nominated for a skilled position by an approved sponsor",
        "Have the right skills to do the job",
        "Meet the relevant English language requirements"
      ]
    }
  },
  "parent_url": "https://immi.homeaffairs.gov.au/visas/getting-a-visa/visa-listing",
  "depth": 1
}